mvanet/__init__.py
mvanet/model/MVANet.py
mvanet/model/SwinTransformer.py
mvanet/model/__init__.py
mvanet/predictor.py
mvanet/utils/__init__.py
mvanet/utils/config.py
mvanet/utils/dataset_strategy_fpn.py
mvanet/utils/misc.py
mvanet/utils/saliency_metric.py
mvanet/utils/test_data.py
mvanet-0.3.0.dist-info/LICENSE
mvanet-0.3.0.dist-info/METADATA
mvanet-0.3.0.dist-info/WHEEL
mvanet-0.3.0.dist-info/RECORD
