Metadata-Version: 2.3
Name: mvanet
Version: 0.3.0
Summary: 
Author: Shunsuke KITADA
Author-email: shunsuke.kitada.0831@gmail.com
Requires-Python: >=3.10
Classifier: Programming Language :: Python :: 3
Classifier: Programming Language :: Python :: 3.10
Classifier: Programming Language :: Python :: 3.11
Classifier: Programming Language :: Python :: 3.12
Classifier: Programming Language :: Python :: 3.13
Requires-Dist: einops (>=0.8.0)
Requires-Dist: timm (>=1.0.7)
Requires-Dist: torch (>=2.0.0)
Requires-Dist: torchvision (>=0.15.0)
Requires-Dist: ttach (>=0.0.3)
